<?xml version='1.1' encoding='UTF-8'?>
<com.cloudbees.plugins.credentials.SystemCredentialsProvider plugin="credentials@1415.v831096eb_5534">
  <domainCredentialsMap class="hudson.util.CopyOnWriteMap$Hash">
    <entry>
      <com.cloudbees.plugins.credentials.domains.Domain>
        <specifications/>
      </com.cloudbees.plugins.credentials.domains.Domain>
      <java.util.concurrent.CopyOnWriteArrayList>
        <com.cloudbees.plugins.credentials.impl.UsernamePasswordCredentialsImpl>
          <scope>GLOBAL</scope>
          <id>6e96b319-7e14-41e8-a708-a281387e55a0</id>
          <description></description>
          <username>ec2-user</username>
          <password>{AQAAABAAAAAQ+TUOiVco/ogxDjcj/qC1FzDjuFl3A0UBVhAdQEeSanQ=}</password>
          <usernameSecret>false</usernameSecret>
        </com.cloudbees.plugins.credentials.impl.UsernamePasswordCredentialsImpl>
        <com.cloudbees.plugins.credentials.impl.UsernamePasswordCredentialsImpl>
          <scope>GLOBAL</scope>
          <id>f8ddc1c1-ae6d-4ef2-af70-ef0c3c6a26c6</id>
          <description></description>
          <username>ubuntu</username>
          <password>{AQAAABAAAAAQLZYSsqfTvKRVO1WeGyds6uR+KE85nusOY7tlWiCf0PM=}</password>
          <usernameSecret>false</usernameSecret>
        </com.cloudbees.plugins.credentials.impl.UsernamePasswordCredentialsImpl>
      </java.util.concurrent.CopyOnWriteArrayList>
    </entry>
  </domainCredentialsMap>
</com.cloudbees.plugins.credentials.SystemCredentialsProvider>